reling/__init__.py
reling/config.py
reling/data.py
reling/gpt_log.py
reling/reling.py
reling/app/__init__.py
reling/app/app.py
reling/app/db.py
reling/app/default_content.py
reling/app/exceptions.py
reling/app/types.py
reling/app/commands/__init__.py
reling/app/commands/archive.py
reling/app/commands/db.py
reling/app/commands/delete.py
reling/app/commands/gpt_log.py
reling/app/commands/history.py
reling/app/commands/list.py
reling/app/commands/rename.py
reling/app/commands/show.py
reling/app/commands/unarchive.py
reling/app/commands/create/__init__.py
reling/app/commands/create/generation.py
reling/app/commands/create/storage.py
reling/app/commands/exam/__init__.py
reling/app/commands/exam/execution.py
reling/app/commands/exam/explanation.py
reling/app/commands/exam/input.py
reling/app/commands/exam/presentation.py
reling/app/commands/exam/repetition.py
reling/app/commands/exam/scoring.py
reling/app/commands/exam/skips.py
reling/app/commands/exam/storage.py
reling/app/commands/exam/streaks.py
reling/app/commands/exam/types.py
reling/app/commands/stats/__init__.py
reling/app/commands/stats/checkpoints.py
reling/app/commands/stats/filter.py
reling/app/commands/stats/grammar_stats.py
reling/app/commands/stats/modalities.py
reling/app/commands/stats/pos.py
reling/app/commands/stats/progress.py
reling/app/commands/stats/regular_stats.py
reling/app/commands/stats/table_str_enum.py
reling/app/translation/__init__.py
reling/app/translation/consolidation.py
reling/app/translation/exceptions.py
reling/app/translation/operation.py
reling/app/translation/storage.py
reling/app/translation/translation.py
reling/asr/__init__.py
reling/data/languages.csv
reling/data/speakers.csv
reling/data/styles.csv
reling/data/topics.csv
reling/db/__init__.py
reling/db/base.py
reling/db/enums.py
reling/db/migrations.py
reling/db/helpers/__init__.py
reling/db/helpers/content.py
reling/db/helpers/ids.py
reling/db/helpers/languages.py
reling/db/helpers/modifiers.py
reling/db/models/__init__.py
reling-1.15.10.dist-info/licenses/LICENSE
reling-1.15.10.dist-info/METADATA
reling-1.15.10.dist-info/WHEEL
reling-1.15.10.dist-info/entry_points.txt
reling-1.15.10.dist-info/top_level.txt
reling-1.15.10.dist-info/RECORD
