Metadata-Version: 2.4
Name: reling
Version: 1.15.10
Summary: Command-line tool for learning foreign languages through iterative translation with AI-generated feedback
Home-page: https://github.com/danmysak/reling
Author: Danylo Mysak
Author-email: danmysak@gmail.com
Project-URL: Bug Tracker, https://github.com/danmysak/reling/issues
Classifier: Programming Language :: Python :: 3
Classifier: License :: OSI Approved :: MIT License
Classifier: Operating System :: OS Independent
Requires-Python: >=3.12
License-File: LICENSE
Requires-Dist: lcs2>=2.0
Requires-Dist: nanoid
Requires-Dist: openai>=1.88
Requires-Dist: prompt_toolkit
Requires-Dist: pytz
Requires-Dist: SQLAlchemy>=2.0
Requires-Dist: tqdm>=4.0
Requires-Dist: typer
Requires-Dist: wcwidth
Provides-Extra: audio
Requires-Dist: pyaudio; extra == "audio"
Requires-Dist: gtts; extra == "audio"
Requires-Dist: pydub; extra == "audio"
Provides-Extra: image
Requires-Dist: opencv-python; extra == "image"
Provides-Extra: grammar
Requires-Dist: stanza; extra == "grammar"
Requires-Dist: numpy<2.0; extra == "grammar"
Provides-Extra: test
Requires-Dist: pytest; extra == "test"
Dynamic: license-file
